agents_experimental/__init__.py
agents_experimental/ai_client.py
agents_experimental/data_classes.py
agents_experimental/agents/__init__.py
agents_experimental/agents/agent.py
agents_experimental/agents/agents_api.py
agents_experimental/agents/session.py
agents_experimental/api/__init__.py
agents_experimental/api/base.py
agents_experimental/tools/__init__.py
agents_experimental/tools/function_tools.py
agents_experimental-0.1.17.dist-info/METADATA
agents_experimental-0.1.17.dist-info/WHEEL
agents_experimental-0.1.17.dist-info/RECORD
