Metadata-Version: 2.4
Name: agents_experimental
Version: 0.1.17
Summary: Experimental SDK for interacting with Atlas AI agents
Author-email: Kelvin  Sundli <kelvin.sundli@gmail.com>
Requires-Python: >=3.8
Requires-Dist: cognite-sdk>=6.0.0
Requires-Dist: griffe>=1.4.0
Requires-Dist: pydantic>=2.7.0
